pythonparts/__init__.py
pythonparts/config.py
pythonparts/src/__init__.py
pythonparts/src/config.py
pythonparts/src/exceptions.py
pythonparts/src/utils.py
pythonparts/src/geometry/__init__.py
pythonparts/src/geometry/concrete_cover.py
pythonparts/src/geometry/coords.py
pythonparts/src/geometry/cuboid.py
pythonparts/src/geometry/scene.py
pythonparts/src/geometry/space.py
pythonparts/src/geometry/space_state.py
pythonparts/src/handles/__init__.py
pythonparts/src/handles/handle.py
pythonparts/src/properties/__init__.py
pythonparts/src/properties/com_prop.py
pythonparts/src/public/__init__.py
pythonparts/src/public/interface.py
pythonparts/src/public/tools.py
pythonparts/src/reinforcement/__init__.py
pythonparts/src/reinforcement/longbar.py
pythonparts/src/reinforcement/mesh.py
pythonparts/src/reinforcement/reinforcement.py
pythonparts/src/reinforcement/stirrup.py
pythonparts/tests/__init__.py
pythonparts/tests/conftest.py
pythonparts/tests/test_coords.py
pythonparts/tests/test_geometry.py
pythonparts/tests/test_handles.py
pythonparts/tests/test_imports.py
pythonparts/tests/test_interface.py
pythonparts/tests/test_other.py
pythonparts/tests/test_reinforcement.py
pythonparts/tests/utils.py
pythonparts-1.0.0.dist-info/METADATA
pythonparts-1.0.0.dist-info/WHEEL
pythonparts-1.0.0.dist-info/top_level.txt
pythonparts-1.0.0.dist-info/RECORD
