Metadata-Version: 2.1
Name: pythonparts
Version: 1.0.0
Summary: PythonParts library
Author: Yaroslav Oliinyk
License: Commercial Standard License
Requires-Dist: openpyxl ==3.0.7
